README.md
setup.py
wordpress_search_results_scraper/__init__.py
wordpress_search_results_scraper.egg-info/PKG-INFO
wordpress_search_results_scraper.egg-info/SOURCES.txt
wordpress_search_results_scraper.egg-info/dependency_links.txt
wordpress_search_results_scraper.egg-info/requires.txt
wordpress_search_results_scraper.egg-info/top_level.txt